alibabacloud_intelligentcreation20240313/__init__.py
alibabacloud_intelligentcreation20240313/client.py
alibabacloud_intelligentcreation20240313/models/__init__.py
alibabacloud_intelligentcreation20240313/models/_add_document_info.py
alibabacloud_intelligentcreation20240313/models/_add_document_result.py
alibabacloud_intelligentcreation20240313/models/_add_text_feedback_request.py
alibabacloud_intelligentcreation20240313/models/_add_text_feedback_response.py
alibabacloud_intelligentcreation20240313/models/_add_text_feedback_response_body.py
alibabacloud_intelligentcreation20240313/models/_anchor_response.py
alibabacloud_intelligentcreation20240313/models/_batch_add_document_request.py
alibabacloud_intelligentcreation20240313/models/_batch_add_document_response.py
alibabacloud_intelligentcreation20240313/models/_batch_add_document_result.py
alibabacloud_intelligentcreation20240313/models/_batch_create_aicoach_task_request.py
alibabacloud_intelligentcreation20240313/models/_batch_create_aicoach_task_response.py
alibabacloud_intelligentcreation20240313/models/_batch_create_aicoach_task_response_body.py
alibabacloud_intelligentcreation20240313/models/_batch_get_project_task_request.py
alibabacloud_intelligentcreation20240313/models/_batch_get_project_task_response.py
alibabacloud_intelligentcreation20240313/models/_batch_get_project_task_response_body.py
alibabacloud_intelligentcreation20240313/models/_batch_get_project_task_shrink_request.py
alibabacloud_intelligentcreation20240313/models/_batch_get_train_task_request.py
alibabacloud_intelligentcreation20240313/models/_batch_get_train_task_response.py
alibabacloud_intelligentcreation20240313/models/_batch_get_train_task_response_body.py
alibabacloud_intelligentcreation20240313/models/_batch_get_train_task_shrink_request.py
alibabacloud_intelligentcreation20240313/models/_batch_get_video_clip_task_request.py
alibabacloud_intelligentcreation20240313/models/_batch_get_video_clip_task_response.py
alibabacloud_intelligentcreation20240313-2.16.2.dist-info/LICENSE
alibabacloud_intelligentcreation20240313-2.16.2.dist-info/METADATA
alibabacloud_intelligentcreation20240313-2.16.2.dist-info/WHEEL
alibabacloud_intelligentcreation20240313-2.16.2.dist-info/top_level.txt
alibabacloud_intelligentcreation20240313-2.16.2.dist-info/RECORD
